{
  "updated": "2026-05-18",
  "brian_harris_bmw": {
    "q1_2026": {
      "sessions": 69564,
      "users": 56999,
      "newUsers": 40020,
      "pageviews": 250322,
      "pagesPerSession": 3.6
    },
    "q1_prev": {
      "sessions": 59432,
      "users": 48951,
      "newUsers": 33654,
      "pageviews": 214036,
      "pagesPerSession": 3.6
    },
    "last30": {
      "sessions": 23397,
      "users": 19370,
      "newUsers": 13768,
      "pageviews": 82368,
      "pagesPerSession": 3.52
    },
    "last60": {
      "sessions": 45364,
      "users": 37071,
      "newUsers": 25740,
      "pageviews": 165509,
      "pagesPerSession": 3.65
    },
    "sources": [
      {
        "source": "google",
        "medium": "cpc",
        "sessions": 27575,
        "users": 20994
      },
      {
        "source": "(direct)",
        "medium": "(none)",
        "sessions": 16403,
        "users": 11103
      },
      {
        "source": "google",
        "medium": "organic",
        "sessions": 16048,
        "users": 7122
      },
      {
        "source": "bing",
        "medium": "organic",
        "sessions": 1653,
        "users": 972
      },
      {
        "source": "amp",
        "medium": "text",
        "sessions": 1619,
        "users": 1051
      },
      {
        "source": "vinurl.com",
        "medium": "referral",
        "sessions": 1046,
        "users": 689
      },
      {
        "source": "bmwusa.com",
        "medium": "referral",
        "sessions": 961,
        "users": 564
      },
      {
        "source": "app.podium.com",
        "medium": "referral",
        "sessions": 732,
        "users": 12
      },
      {
        "source": "yahoo",
        "medium": "organic",
        "sessions": 600,
        "users": 323
      },
      {
        "source": "facebook",
        "medium": "cpc",
        "sessions": 332,
        "users": 319
      },
      {
        "source": "(not set)",
        "medium": "(not set)",
        "sessions": 326,
        "users": 304
      },
      {
        "source": "duckduckgo",
        "medium": "organic",
        "sessions": 309,
        "users": 101
      },
      {
        "source": "(data not available)",
        "medium": "(data not available)",
        "sessions": 223,
        "users": 223
      },
      {
        "source": "jlemail",
        "medium": "email1",
        "sessions": 222,
        "users": 178
      },
      {
        "source": "brianharrisautogroup.com",
        "medium": "referral",
        "sessions": 213,
        "users": 19
      },
      {
        "source": "autotrader.com",
        "medium": "referral",
        "sessions": 179,
        "users": 118
      },
      {
        "source": "m.facebook.com",
        "medium": "referral",
        "sessions": 165,
        "users": 146
      },
      {
        "source": "carfax.com",
        "medium": "referral",
        "sessions": 132,
        "users": 82
      },
      {
        "source": "visor.vin",
        "medium": "referral",
        "sessions": 131,
        "users": 82
      },
      {
        "source": "amp",
        "medium": "email",
        "sessions": 89,
        "users": 75
      }
    ],
    "mobile_pct": 65.4
  },
  "audi_baton_rouge": {
    "q1_2026": {
      "sessions": 45348,
      "users": 39046,
      "newUsers": 31587,
      "pageviews": 109026,
      "pagesPerSession": 2.4
    },
    "q1_prev": {
      "sessions": 51963,
      "users": 44552,
      "newUsers": 35757,
      "pageviews": 117429,
      "pagesPerSession": 2.26
    },
    "last30": {
      "sessions": 15086,
      "users": 13244,
      "newUsers": 10774,
      "pageviews": 31688,
      "pagesPerSession": 2.1
    },
    "last60": {
      "sessions": 31374,
      "users": 27268,
      "newUsers": 22075,
      "pageviews": 71048,
      "pagesPerSession": 2.26
    },
    "sources": [
      {
        "source": "google",
        "medium": "organic",
        "sessions": 11497,
        "users": 5579
      },
      {
        "source": "(direct)",
        "medium": "(none)",
        "sessions": 9720,
        "users": 6553
      },
      {
        "source": "google",
        "medium": "cpc",
        "sessions": 4611,
        "users": 3743
      },
      {
        "source": "cdn.flashtalking.com",
        "medium": "referral",
        "sessions": 3291,
        "users": 3205
      },
      {
        "source": "ig",
        "medium": "paid",
        "sessions": 2578,
        "users": 2490
      },
      {
        "source": "(not set)",
        "medium": "(not set)",
        "sessions": 2187,
        "users": 2162
      },
      {
        "source": "autotrader.com",
        "medium": "social",
        "sessions": 1867,
        "users": 1425
      },
      {
        "source": "fb",
        "medium": "paid",
        "sessions": 1666,
        "users": 1560
      },
      {
        "source": "audiusa.com",
        "medium": "referral",
        "sessions": 1316,
        "users": 968
      },
      {
        "source": "facebook",
        "medium": "paid",
        "sessions": 1031,
        "users": 996
      },
      {
        "source": "bing",
        "medium": "organic",
        "sessions": 951,
        "users": 522
      },
      {
        "source": "vinurl.com",
        "medium": "referral",
        "sessions": 739,
        "users": 537
      },
      {
        "source": "imasdk.googleapis.com",
        "medium": "referral",
        "sessions": 626,
        "users": 625
      },
      {
        "source": "pinterest.com",
        "medium": "referral",
        "sessions": 473,
        "users": 423
      },
      {
        "source": "tpc.googlesyndication.com",
        "medium": "referral",
        "sessions": 352,
        "users": 351
      },
      {
        "source": "yahoo",
        "medium": "organic",
        "sessions": 274,
        "users": 158
      },
      {
        "source": "m.facebook.com",
        "medium": "referral",
        "sessions": 235,
        "users": 218
      },
      {
        "source": "cargurus.com",
        "medium": "referral",
        "sessions": 229,
        "users": 152
      },
      {
        "source": "banners2.esm1.net",
        "medium": "referral",
        "sessions": 168,
        "users": 168
      },
      {
        "source": "autotrader.com",
        "medium": "referral",
        "sessions": 145,
        "users": 66
      }
    ],
    "mobile_pct": 66.5
  },
  "bmw_jackson": {
    "q1_2026": {
      "sessions": 74227,
      "users": 65642,
      "newUsers": 50646,
      "pageviews": 161888,
      "pagesPerSession": 2.18
    },
    "q1_prev": {
      "sessions": 49945,
      "users": 43070,
      "newUsers": 31254,
      "pageviews": 126427,
      "pagesPerSession": 2.53
    },
    "last30": {
      "sessions": 25931,
      "users": 23043,
      "newUsers": 17703,
      "pageviews": 55792,
      "pagesPerSession": 2.15
    },
    "last60": {
      "sessions": 52310,
      "users": 46341,
      "newUsers": 35753,
      "pageviews": 111067,
      "pagesPerSession": 2.12
    },
    "sources": [
      {
        "source": "google",
        "medium": "cpc",
        "sessions": 39328,
        "users": 29918
      },
      {
        "source": "(direct)",
        "medium": "(none)",
        "sessions": 12469,
        "users": 9425
      },
      {
        "source": "google",
        "medium": "organic",
        "sessions": 10545,
        "users": 6138
      },
      {
        "source": "facebook",
        "medium": "cpc",
        "sessions": 5156,
        "users": 4103
      },
      {
        "source": "(not set)",
        "medium": "(not set)",
        "sessions": 1756,
        "users": 1586
      },
      {
        "source": "bing",
        "medium": "organic",
        "sessions": 835,
        "users": 455
      },
      {
        "source": "(data not available)",
        "medium": "(data not available)",
        "sessions": 436,
        "users": 431
      },
      {
        "source": "yahoo",
        "medium": "organic",
        "sessions": 329,
        "users": 184
      },
      {
        "source": "bmw-retailer.email-dealer.com",
        "medium": "referral",
        "sessions": 323,
        "users": 324
      },
      {
        "source": "facebook.com",
        "medium": "referral",
        "sessions": 283,
        "users": 275
      },
      {
        "source": "m.facebook.com",
        "medium": "referral",
        "sessions": 227,
        "users": 218
      },
      {
        "source": "autotrader.com",
        "medium": "referral",
        "sessions": 220,
        "users": 118
      },
      {
        "source": "bmwusa.com",
        "medium": "referral",
        "sessions": 208,
        "users": 141
      },
      {
        "source": "cars.com",
        "medium": "referral",
        "sessions": 142,
        "users": 83
      },
      {
        "source": "focus.dealer.reyrey.net",
        "medium": "referral",
        "sessions": 119,
        "users": 3
      },
      {
        "source": "duckduckgo",
        "medium": "organic",
        "sessions": 111,
        "users": 55
      },
      {
        "source": "jlemail",
        "medium": "email1",
        "sessions": 89,
        "users": 64
      },
      {
        "source": "fb",
        "medium": "paid",
        "sessions": 69,
        "users": 67
      },
      {
        "source": "visor.vin",
        "medium": "referral",
        "sessions": 48,
        "users": 26
      },
      {
        "source": "creditacceptance.com",
        "medium": "referral",
        "sessions": 43,
        "users": 34
      }
    ],
    "mobile_pct": 70.0
  }
}